multimatching/__init__.py
multimatching/bottleneck.py
multimatching/example.py
multimatching/test_bottleneck.py
multimatching/max-flow/__init__.py
multimatching/max-flow/capacity_scaling.py
multimatching/max-flow/dinics.py
multimatching/max-flow/flow.py
multimatching/max-flow/ford_fulkerson.py
multimatching/max-flow/graph.py
multimatching/max-flow/graph_test.py
multimatching-0.1.0.dist-info/LICENSE
multimatching-0.1.0.dist-info/METADATA
multimatching-0.1.0.dist-info/WHEEL
multimatching-0.1.0.dist-info/top_level.txt
multimatching-0.1.0.dist-info/RECORD
