Metadata-Version: 2.1
Name: multimatching
Version: 0.1.0
Summary: A Python package for computing bottleneck distance.
Home-page: https://github.com/donsheehy/multimatching
Author: Rohak Rastogi, Donald R. Sheehy and Siddharth Sheth
Author-email: don.r.sheehy@gmail.com
Classifier: Programming Language :: Python :: 3
Classifier: License :: OSI Approved :: MIT License
Classifier: Operating System :: OS Independent
Requires-Python: >=3.6
License-File: LICENSE
Requires-Dist: pdsketch
Requires-Dist: ortools
